damnode/__init__.py
damnode/cli.py
damnode/core.py
damnode-0.0.3.dist-info/top_level.txt
damnode-0.0.3.dist-info/entry_points.txt
damnode-0.0.3.dist-info/METADATA
damnode-0.0.3.dist-info/DESCRIPTION.rst
damnode-0.0.3.dist-info/metadata.json
damnode-0.0.3.dist-info/WHEEL
damnode-0.0.3.dist-info/RECORD
